<dockpanel halign='stretch' valign='stretch'>
  <resourcecollection>
    <color key="buckshot_blue" value="#165284"></color>

    <styletemplate key="iotext">
       <setters>
          <setter property="margin" value="15,0,0,0" />
          <setter property="fontSize" value="20" />
       </setters>
    </styletemplate>
    <styletemplate key='headerText'>
       <setters>
          <setter property='fontSize' value='18' />
          <setter property='margin' value='15,0,10,0' />
       </setters>
    </styletemplate>
    <styletemplate key='defaultText'>
       <setters>
          <setter property='fontSize' value='14' />
          <setter property='margin' value='0,3' />
       </setters>
    </styletemplate>
  </resourcecollection>

  <border padding='5' dockpanel.dock='top' background='{resource buckshot_blue}'>
	    <stack orientation='horizontal'>
	       <hyperlink valign='center' navigateto='http://www.buckshotui.org/'>
		       <image width='35' sourceuri='web/resources/buckshot_logo.png' alt='Buckshot Logo' />
		       </hyperlink>
	       <textblock margin='0,0,0,5' valign='center' foreground='White' text='Buckshot Sandbox' />
	       <textblock margin='0,0,0,5' valign='center' foreground='White' fontsize='10' text='alpha' />
	    </stack>
  </border>

  <stack margin='5' dockpanel.dock='left' minWidth='250'>
    <textblock maxwidth='250' text="Select a sample below, or create your own in the text area."/>
    <border shadowx='{resource theme_shadow_x}'
            shadowy='{resource theme_shadow_y}'
            shadowblur='{resource theme_shadow_blur}'
            valign='stretch'
            halign='stretch'
            background='{resource theme_background_light}' borderthickness='{resource theme_border_thickness}' bordercolor='{resource theme_border_color}' margin='0,5,10,0'>
     	<accordion selectionmode='single' halign='stretch'>
     	   <accordionitem>
     	     <header>
     	       <textblock style='{resource defaultText}' text='Application Demos' />
     	     </header>
     	     <body>
     	        <treeview on.treenodeselected='selection_handler'>
                   <treenode header='Calculator' tag='app.calc' />
                   <treenode header='Analog Clock' tag='clock' />
                   <treenode header='Simple Todo List' tag='app.todo' />
	  	        </treeview>
     	     </body>
     	   </accordionitem>
     	   <accordionitem>
     	     <header>
     	       <textblock style='{resource defaultText}' text='Elements' />
     	     </header>
     	     <body>
     	        <treeview on.treenodeselected='selection_handler'>
			     	<treenode header='TextBlock' tag='textblock' />
			     	<treenode header='Stack' tag='stack' />
			     	<treenode header='Border' tag='border' />
			     	<treenode header='Grid' tag='grid' />
			     	<treenode header='RawHtml' tag='rawhtml' />
			     	<treenode header='LayoutCanvas' tag='layoutcanvas' />
			     	<treenode header='3D Transformations' tag='transforms' />
			        <treenode header='Shadows' tag='shadows' />
	  	        </treeview>
     	     </body>
     	   </accordionitem>
     	   <accordionitem>
     	     <header>
     	       <textblock style='{resource defaultText}' text='Controls' />
     	     </header>
     	     <body>
     	        <treeview on.treenodeselected='selection_handler'>
     	            <treenode header='Menus' tag='menus' />
			        <treenode header='TabControl' tag='tabcontrol' />
			     	<treenode header='TreeView' tag='treeview' />
			     	<treenode header='DockPanel' tag='dockpanel' />
			     	<treenode header='Accordion' tag='accordion' />
			     	<treenode header='ListBox' tag='listbox' />
			     	<treenode header='ModalDialog' tag='modaldialog' />
			     	<treenode header='Popup' tag='popup' />
			     	<treenode header='DropDownList' tag='dropdownlist' />
			     	<treenode header='TextBox' tag='textbox' />
			     	<treenode header='Slider' tag='slider' />
			     	<treenode header='Button' tag='button' />
			     	<treenode header='RadioButton' tag='radiobutton' />
			     	<treenode header='CheckBox' tag='checkbox' />
			     	<treenode header='Hyperlink' tag='hyperlink' />
	  	        </treeview>
     	     </body>
     	   </accordionitem>
     	   <accordionitem>
     	     <header>
     	       <textblock style='{resource defaultText}' text='Binding Demos' />
     	     </header>
     	     <body>
     	        <treeview on.treenodeselected='selection_handler'>
			     	<treenode header='Resource Binding' tag='resources' />
			     	<treenode header='Element Binding' tag='elementbinding' />
			     	<treenode header='Data Binding' tag='databinding' />
			     	<treenode header='Binding To Collections' tag='collections' />
	  	        </treeview>
     	     </body>
     	   </accordionitem>
     	   <accordionitem>
     	     <header>
     	       <textblock style='{resource defaultText}' text='Media Extensions' />
     	     </header>
     	     <body>
     	        <treeview on.treenodeselected='selection_handler'>
			     	<treenode header='YouTube' tag='youtube' />
			     	<treenode header='Hulu' tag='hulu' />
			     	<treenode header='Vimeo' tag='vimeo' />
			     	<treenode header='FunnyOrDie' tag='funnyordie' />
	  	        </treeview>
     	     </body>
     	   </accordionitem>
     	</accordion>
    </border>
		<plusone annotation='inline' width='200' size='medium' dockpanel.dock='right'></plusone>
  </stack>

  <dockpanel dockpanel.dock='left' filllast='true'>
  	<border
  		shadowcolor='Gray' shadowx='2' shadowy='2' shadowblur='3'
  		dockpanel.dock='top' padding='5' background='{resource theme_light_brush}' content='{data renderedOutput}'
  		margin="5" minheight='200' maxheight='600'
    	borderThickness="1" verticalscrollenabled='true' borderColor="{resource theme_border_color}" />

    <stack dockpanel.dock='top' margin='0,0,0,5' orientation="horizontal">
       <button on.click='refresh_handler' content="Generate Output"></button>
       <button on.click='clearAll_handler' content="Clear All"></button>
    </stack>

    <textarea fontsize='18' dockpanel.dock='bottom' minwidth='650' minheight='300' margin='0,10,0,5'
	    placeholder="Type something here or select one of the samples to the left."
	    spellcheck="false"
	  	text='{data templateText, mode=twoway}' />

  </dockpanel>
</dockpanel>